FrickDB/__init__.py
FrickDB/__main__.py
FrickDB/db.py
FrickDB/exceptions.py
FrickDB-0.0.2.dist-info/LICENSE
FrickDB-0.0.2.dist-info/METADATA
FrickDB-0.0.2.dist-info/WHEEL
FrickDB-0.0.2.dist-info/top_level.txt
FrickDB-0.0.2.dist-info/RECORD
