Metadata-Version: 2.1
Name: FrickDB
Version: 0.0.2
Summary: A wierd JSON-based database.
Home-page: https://github.com/4041RebL/FrickDB
Author: Harsh Vardhan
Author-email: vardhan.harsh4041@gmail.com
License: UNKNOWN
Platform: UNKNOWN
Classifier: Programming Language :: Python :: 3
Classifier: License :: OSI Approved :: MIT License
Classifier: Operating System :: OS Independent
Requires-Python: >=3.6
